setup.py
MySerializator.egg-info/PKG-INFO
MySerializator.egg-info/SOURCES.txt
MySerializator.egg-info/dependency_links.txt
MySerializator.egg-info/top_level.txt
serializers/__init__.py
serializers/factory.py
serializers/json/__init__.py
serializers/json/json_serializer.py
serializers/xml/__init__.py
serializers/xml/xml_serializer.py
source/__init__.py
source/constants.py
source/meta_serializer.py
source/serializer.py
source/serializer_shell.py
tests/__init__.py
tests/serialization_tests.py